deeplx_tr/__init__.py
deeplx_tr/__main__.py
deeplx_tr/__main__.py-
deeplx_tr/deeplx_client.py
deeplx_tr/deeplx_client_async.py
deeplx_tr/deeplx_tr.py
deeplx_tr/deeplx_tr.py-
deeplx_tr-0.1.0a1.dist-info/METADATA
deeplx_tr-0.1.0a1.dist-info/WHEEL
deeplx_tr-0.1.0a1.dist-info/entry_points.txt
deeplx_tr-0.1.0a1.dist-info/licenses/LICENSE
deeplx_tr-0.1.0a1.dist-info/RECORD
