Metadata-Version: 2.3
Name: deeplx-tr
Version: 0.1.0a1
Summary:  TODO 
Author: ffreemt
License-Expression: MIT
License-File: LICENSE
Requires-Python: >=3.8
Requires-Dist: httpx>=0.27.0
Requires-Dist: loguru>=0.7.2
Requires-Dist: pyperclip>=1.8.2
Requires-Dist: rich>=13.7.1
Requires-Dist: set-loglevel>=0.1.2
Requires-Dist: typer>=0.12.1
